aionsxt/__init__.py
aionsxt/nsxt_client.py
aionsxt/nsxt_export.py
aionsxt-0.1.0.post4.dist-info/METADATA
aionsxt-0.1.0.post4.dist-info/WHEEL
aionsxt-0.1.0.post4.dist-info/top_level.txt
aionsxt-0.1.0.post4.dist-info/RECORD
