Metadata-Version: 2.4
Name: aionsxt
Version: 0.1.0.post4
Summary: Python asyncio package for VMware NSX
Author-email: Antoine Richado <fordian68@gmail.com>
Classifier: Programming Language :: Python :: 3
Classifier: Operating System :: OS Independent
Requires-Dist: aiofiles==24.1.0
Requires-Dist: aiohttp==3.11.7
Requires-Dist: asyncio==3.4.3
Requires-Dist: colorama==0.4.6
Requires-Dist: types-colorama==0.4.15.20240311
Requires-Dist: types-requests==2.32.0.20241016
Requires-Dist: typing==3.7.4.3
Requires-Dist: typing_extensions==4.12.2
Requires-Dist: urllib3==2.2.3
